CHANGELOG.rst
jeepito-0.5.1.dist-info/METADATA
jeepito-0.5.1.dist-info/WHEEL
jeepito-0.5.1.dist-info/entry_points.txt
jeepito-0.5.1.dist-info/licenses/LICENSE
jeepito/__init__.py
jeepito/domain/model.py
jeepito/py.typed
jeepito/service/_async/eventstream.py
jeepito/service/_async/registry.py
jeepito/service/_async/repository.py
jeepito/service/_async/unit_of_work.py
jeepito/service/_sync/eventstream.py
jeepito/service/_sync/registry.py
jeepito/service/_sync/repository.py
jeepito/service/_sync/unit_of_work.py
jeepito/service/eventstream.py
jeepito/typing.py
jeepito-0.5.1.dist-info/RECORD
